oneNeuron/__init__.py
oneNeuron/all_utils.py
oneNeuron/perceptron.py
OneNeuron_PyPI_YogeshRajgure-1.0.1.dist-info/LICENSE
OneNeuron_PyPI_YogeshRajgure-1.0.1.dist-info/METADATA
OneNeuron_PyPI_YogeshRajgure-1.0.1.dist-info/WHEEL
OneNeuron_PyPI_YogeshRajgure-1.0.1.dist-info/top_level.txt
OneNeuron_PyPI_YogeshRajgure-1.0.1.dist-info/RECORD
