Metadata-Version: 2.1
Name: OneNeuron_PyPI-YogeshRajgure
Version: 1.0.1
Summary: Its an implementation of perceptron
Home-page: https://github.com/pypa/sampleproject
Author: YogeshRajgure
Author-email: yogeshrajgure.vraj@gmail.com
License: UNKNOWN
Project-URL: Bug Tracker, https://github.com/YogeshRajgure/OneNeuron_PyPI/issues
Platform: UNKNOWN
Classifier: Programming Language :: Python :: 3
Classifier: License :: OSI Approved :: MIT License
Classifier: Operating System :: OS Independent
Requires-Python: >=3.7
License-File: LICENSE
